pygmol/__init__.py
pygmol/abc.py
pygmol/chemistry.py
pygmol/equations.py
pygmol/model.py
pygmol/plasma_parameters.py
pygmol-1.1.2.dist-info/LICENSE
pygmol-1.1.2.dist-info/METADATA
pygmol-1.1.2.dist-info/WHEEL
pygmol-1.1.2.dist-info/top_level.txt
pygmol-1.1.2.dist-info/RECORD
