Metadata-Version: 2.1
Name: pygmol
Version: 1.1.2
Summary: A plasma global model in python
Home-page: https://github.com/hanicinecm/pygmol/
Author: Martin Hanicinec
Author-email: hanicinecm@gmail.com
License: UNKNOWN
Project-URL: Bug Reports, https://github.com/hanicinecm/pygmol/issues
Project-URL: Documentation, https://github.com/hanicinecm/pygmol/tree/master/docs/doc_index.rst
Keywords: plasma physics chemistry global model
Platform: UNKNOWN
Classifier: Development Status :: 4 - Beta
Classifier: Intended Audience :: Science/Research
Classifier: Topic :: Scientific/Engineering :: Physics
Classifier: Topic :: Scientific/Engineering :: Chemistry
Classifier: Topic :: Scientific/Engineering :: Astronomy
Classifier: License :: OSI Approved :: MIT License
Classifier: Programming Language :: Python :: 3
Classifier: Programming Language :: Python :: 3.7
Classifier: Programming Language :: Python :: 3.8
Classifier: Programming Language :: Python :: 3.9
Classifier: Programming Language :: Python :: 3.10
Classifier: Programming Language :: Python :: 3 :: Only
Classifier: Operating System :: OS Independent
Requires-Python: >=3.7
License-File: LICENSE
Requires-Dist: scipy (==1.7.3)
Requires-Dist: pyvalem (>=2.5.4)
Requires-Dist: pandas
Provides-Extra: dev
Requires-Dist: pytest-cov ; extra == 'dev'
Requires-Dist: black ; extra == 'dev'
Requires-Dist: ipython ; extra == 'dev'
